Metadata-Version: 2.1
Name: telegrambotmsg
Version: 2.0.6
Summary: Telegram Bot
Home-page: UNKNOWN
Author: pola Lowe
Author-email: jhon@dan.org
License: MIT
Keywords: Telegram Bot send msg on private chat
Platform: UNKNOWN
Classifier: Development Status :: 5 - Production/Stable
Classifier: Intended Audience :: Education
Classifier: Operating System :: Microsoft :: Windows :: Windows 10
Classifier: License :: OSI Approved :: MIT License
Classifier: Programming Language :: Python :: 3
License-File: LICENCE.txt
